[
{"name": "nova 13 Pro", "url": "https://www.gsmarena.com/huawei_nova_13_pro-13465.php"},
{"name": "nova 13", "url": "https://www.gsmarena.com/huawei_nova_13-13466.php"},
{"name": "Watch GT 5 Pro", "url": "https://www.gsmarena.com/huawei_watch_gt_5_pro-13349.php"},
{"name": "Watch GT 5", "url": "https://www.gsmarena.com/huawei_watch_gt_5-13350.php"},
{"name": "Watch D2", "url": "https://www.gsmarena.com/huawei_watch_d2-13351.php"},
{"name": "MatePad 12 X", "url": "https://www.gsmarena.com/huawei_matepad_12_x-13352.php"},
{"name": "Mate XT Ultimate", "url": "https://www.gsmarena.com/huawei_mate_xt_ultimate-13320.php"},
{"name": "MatePad Air (2024)", "url": "https://www.gsmarena.com/huawei_matepad_air_(2024)-13251.php"},
{"name": "MatePad Pro 12.2 (2024)", "url": "https://www.gsmarena.com/huawei_matepad_pro_12_2_(2024)-13250.php"},
{"name": "nova Flip", "url": "https://www.gsmarena.com/huawei_nova_flip-13248.php"},
{"name": "MatePad SE 11", "url": "https://www.gsmarena.com/huawei_matepad_se_11-13135.php"},
{"name": "MatePad 11.5 S", "url": "https://www.gsmarena.com/huawei_matepad_11_5_s-12993.php"},
{"name": "Pura 70 Ultra", "url": "https://www.gsmarena.com/huawei_pura_70_ultra-12940.php"},
{"name": "Pura 70 Pro+", "url": "https://www.gsmarena.com/huawei_pura_70_pro+-12941.php"},
{"name": "Pura 70 Pro", "url": "https://www.gsmarena.com/huawei_pura_70_pro-12942.php"},
{"name": "Pura 70", "url": "https://www.gsmarena.com/huawei_pura_70-12943.php"},
{"name": "nova 12i", "url": "https://www.gsmarena.com/huawei_nova_12i-12882.php"},
{"name": "nova 12 SE", "url": "https://www.gsmarena.com/huawei_nova_12_se-12881.php"},
{"name": "nova 12s", "url": "https://www.gsmarena.com/huawei_nova_12s-12880.php"},
{"name": "Pocket 2", "url": "https://www.gsmarena.com/huawei_pocket_2-12837.php"},
{"name": "Enjoy 70z", "url": "https://www.gsmarena.com/huawei_enjoy_70z-12835.php"},
{"name": "nova Y72", "url": "https://www.gsmarena.com/huawei_nova_y72-12807.php"},
{"name": "nova 12 Ultra", "url": "https://www.gsmarena.com/huawei_nova_12_ultra-12761.php"},
{"name": "nova 12 Pro", "url": "https://www.gsmarena.com/huawei_nova_12_pro-12588.php"},
{"name": "nova 12", "url": "https://www.gsmarena.com/huawei_nova_12-12589.php"},
{"name": "nova 12 Lite", "url": "https://www.gsmarena.com/huawei_nova_12_lite-12762.php"},
{"name": "Enjoy 70", "url": "https://www.gsmarena.com/huawei_enjoy_70-12720.php"},
{"name": "MatePad Pro 11 (2024)", "url": "https://www.gsmarena.com/huawei_matepad_pro_11_(2024)-12713.php"},
{"name": "nova 11 SE", "url": "https://www.gsmarena.com/huawei_nova_11_se-12648.php"},
{"name": "Watch Ultimate Design", "url": "https://www.gsmarena.com/huawei_watch_ultimate_design-12607.php"},
{"name": "MatePad Pro 13.2", "url": "https://www.gsmarena.com/huawei_matepad_pro_13_2-12586.php"},
{"name": "Mate 60 RS Ultimate", "url": "https://www.gsmarena.com/huawei_mate_60_rs_ultimate-12585.php"},
{"name": "Watch GT 4", "url": "https://www.gsmarena.com/huawei_watch_gt_4-12563.php"},
{"name": "Mate 60 Pro+", "url": "https://www.gsmarena.com/huawei_mate_60_pro+-12549.php"},
{"name": "Mate X5", "url": "https://www.gsmarena.com/huawei_mate_x5-12550.php"},
{"name": "Mate 60 Pro", "url": "https://www.gsmarena.com/huawei_mate_60_pro-12530.php"},
{"name": "Mate 60", "url": "https://www.gsmarena.com/huawei_mate_60-12539.php"},
{"name": "MatePad 11.5", "url": "https://www.gsmarena.com/huawei_matepad_11_5-12420.php"},
{"name": "MatePad Air", "url": "https://www.gsmarena.com/huawei_matepad_air-12415.php"},
{"name": "nova Y91", "url": "https://www.gsmarena.com/huawei_nova_y91-12290.php"},
{"name": "Watch 4 Pro", "url": "https://www.gsmarena.com/huawei_watch_4_pro-12278.php"},
{"name": "Watch 4", "url": "https://www.gsmarena.com/huawei_watch_4-12279.php"},
{"name": "nova 11i", "url": "https://www.gsmarena.com/huawei_nova_11i-12268.php"},
{"name": "nova Y71", "url": "https://www.gsmarena.com/huawei_nova_y71-12259.php"},
{"name": "Enjoy 60X", "url": "https://www.gsmarena.com/huawei_enjoy_60x-12235.php"},
{"name": "nova 11 Ultra", "url": "https://www.gsmarena.com/huawei_nova_11_ultra-12230.php"},
{"name": "nova 11 Pro", "url": "https://www.gsmarena.com/huawei_nova_11_pro-12233.php"},
{"name": "nova 11", "url": "https://www.gsmarena.com/huawei_nova_11-12234.php"},
{"name": "Mate X3", "url": "https://www.gsmarena.com/huawei_mate_x3-12186.php"},
{"name": "P60 Pro", "url": "https://www.gsmarena.com/huawei_p60_pro-12172.php"},
{"name": "P60", "url": "https://www.gsmarena.com/huawei_p60-12191.php"},
{"name": "P60 Art", "url": "https://www.gsmarena.com/huawei_p60_art-12192.php"},
{"name": "Enjoy 60", "url": "https://www.gsmarena.com/huawei_enjoy_60-12193.php"},
{"name": "Watch Ultimate", "url": "https://www.gsmarena.com/huawei_watch_ultimate-12190.php"},
{"name": "MatePad 11 (2023)", "url": "https://www.gsmarena.com/huawei_matepad_11_(2023)-12185.php"},
{"name": "nova 10 Youth", "url": "https://www.gsmarena.com/huawei_nova_10_youth-12154.php"},
{"name": "Watch Buds", "url": "https://www.gsmarena.com/huawei_watch_buds-12021.php"},
{"name": "Enjoy 50z", "url": "https://www.gsmarena.com/huawei_enjoy_50z-12020.php"},
{"name": "Watch GT 3 SE", "url": "https://www.gsmarena.com/huawei_watch_gt_3_se-11980.php"},
{"name": "Pocket S", "url": "https://www.gsmarena.com/huawei_pocket_s-11970.php"},
{"name": "Watch GT Cyber", "url": "https://www.gsmarena.com/huawei_watch_gt_cyber-11972.php"},
{"name": "nova Y61", "url": "https://www.gsmarena.com/huawei_nova_y61-11968.php"},
{"name": "MatePad C5e", "url": "https://www.gsmarena.com/huawei_matepad_c5e-11942.php"},
{"name": "nova 10 SE", "url": "https://www.gsmarena.com/huawei_nova_10_se-11918.php"},
{"name": "Mate 50 RS Porsche Design", "url": "https://www.gsmarena.com/huawei_mate_50_rs_porsche_design-11858.php"},
{"name": "Mate 50 Pro", "url": "https://www.gsmarena.com/huawei_mate_50_pro-11856.php"},
{"name": "Mate 50E", "url": "https://www.gsmarena.com/huawei_mate_50e-11859.php"},
{"name": "Mate 50", "url": "https://www.gsmarena.com/huawei_mate_50-11857.php"},
{"name": "nova 10z", "url": "https://www.gsmarena.com/huawei_nova_10z-11853.php"},
{"name": "MatePad Pro 11 (2022)", "url": "https://www.gsmarena.com/huawei_matepad_pro_11_(2022)-11720.php"},
{"name": "nova 10 Pro", "url": "https://www.gsmarena.com/huawei_nova_10_pro-11640.php"},
{"name": "nova 10", "url": "https://www.gsmarena.com/huawei_nova_10-11641.php"},
{"name": "nova Y90", "url": "https://www.gsmarena.com/huawei_nova_y90-11639.php"},
{"name": "MatePad 10.4 (2022)", "url": "https://www.gsmarena.com/huawei_matepad_10_4_(2022)-11525.php"},
{"name": "Mate Xs 2", "url": "https://www.gsmarena.com/huawei_mate_xs_2-11503.php"},
{"name": "Watch GT 3 Porsche Design", "url": "https://www.gsmarena.com/huawei_watch_gt_3_porsche_design-11505.php"},
{"name": "Watch GT 3 Pro", "url": "https://www.gsmarena.com/huawei_watch_gt_3_pro-11504.php"},
{"name": "Watch D", "url": "https://www.gsmarena.com/huawei_watch_d-12030.php"},
{"name": "MatePad SE", "url": "https://www.gsmarena.com/huawei_matepad_se-11506.php"},
{"name": "nova 9 SE 5G", "url": "https://www.gsmarena.com/huawei_nova_9_se_5g-11490.php"},
{"name": "nova Y70 Plus", "url": "https://www.gsmarena.com/huawei_nova_y70_plus-11489.php"},
{"name": "P50E", "url": "https://www.gsmarena.com/huawei_p50e-11428.php"},
{"name": "nova 9 SE", "url": "https://www.gsmarena.com/huawei_nova_9_se-11399.php"},
{"name": "P50 Pocket", "url": "https://www.gsmarena.com/huawei_p50_pocket-11280.php"},
{"name": "nova 8 SE 4G", "url": "https://www.gsmarena.com/huawei_nova_8_se_4g-11247.php"},
{"name": "nova Y60", "url": "https://www.gsmarena.com/huawei_nova_y60-11328.php"},
{"name": "Enjoy 20e", "url": "https://www.gsmarena.com/huawei_enjoy_20e-11177.php"},
{"name": "Watch GT Runner", "url": "https://www.gsmarena.com/huawei_watch_gt_runner-11227.php"},
{"name": "Watch Fit mini", "url": "https://www.gsmarena.com/huawei_watch_fit_mini-11176.php"},
{"name": "Watch GT 3", "url": "https://www.gsmarena.com/huawei_watch_gt_3-11171.php"},
{"name": "nova 9 Pro", "url": "https://www.gsmarena.com/huawei_nova_9_pro-11120.php"},
{"name": "nova 9", "url": "https://www.gsmarena.com/huawei_nova_9-11121.php"},
{"name": "nova 8", "url": "https://www.gsmarena.com/huawei_nova_8-11048.php"},
{"name": "P50 Pro", "url": "https://www.gsmarena.com/huawei_p50_pro-11029.php"},
{"name": "P50", "url": "https://www.gsmarena.com/huawei_p50-10788.php"},
{"name": "nova 8 SE Youth", "url": "https://www.gsmarena.com/huawei_nova_8_se_youth-11030.php"},
{"name": "nova 8i", "url": "https://www.gsmarena.com/huawei_nova_8i-11002.php"},
{"name": "Mate 40 Pro 4G", "url": "https://www.gsmarena.com/huawei_mate_40_pro_4g-10985.php"},
{"name": "Mate 40E 4G", "url": "https://www.gsmarena.com/huawei_mate_40e_4g-10986.php"},
{"name": "Mate X2 4G", "url": "https://www.gsmarena.com/huawei_mate_x2_4g-10987.php"},
{"name": "nova 13 Pro", "url": "https://www.gsmarena.com/huawei_nova_13_pro-13465.php"},
{"name": "nova 13", "url": "https://www.gsmarena.com/huawei_nova_13-13466.php"},
{"name": "Watch GT 5 Pro", "url": "https://www.gsmarena.com/huawei_watch_gt_5_pro-13349.php"},
{"name": "Watch GT 5", "url": "https://www.gsmarena.com/huawei_watch_gt_5-13350.php"},
{"name": "Watch D2", "url": "https://www.gsmarena.com/huawei_watch_d2-13351.php"},
{"name": "MatePad 12 X", "url": "https://www.gsmarena.com/huawei_matepad_12_x-13352.php"},
{"name": "Mate XT Ultimate", "url": "https://www.gsmarena.com/huawei_mate_xt_ultimate-13320.php"},
{"name": "MatePad Air (2024)", "url": "https://www.gsmarena.com/huawei_matepad_air_(2024)-13251.php"},
{"name": "MatePad Pro 12.2 (2024)", "url": "https://www.gsmarena.com/huawei_matepad_pro_12_2_(2024)-13250.php"},
{"name": "nova Flip", "url": "https://www.gsmarena.com/huawei_nova_flip-13248.php"},
{"name": "MatePad SE 11", "url": "https://www.gsmarena.com/huawei_matepad_se_11-13135.php"},
{"name": "MatePad 11.5 S", "url": "https://www.gsmarena.com/huawei_matepad_11_5_s-12993.php"},
{"name": "Pura 70 Ultra", "url": "https://www.gsmarena.com/huawei_pura_70_ultra-12940.php"},
{"name": "Pura 70 Pro+", "url": "https://www.gsmarena.com/huawei_pura_70_pro+-12941.php"},
{"name": "Pura 70 Pro", "url": "https://www.gsmarena.com/huawei_pura_70_pro-12942.php"},
{"name": "Pura 70", "url": "https://www.gsmarena.com/huawei_pura_70-12943.php"},
{"name": "nova 12i", "url": "https://www.gsmarena.com/huawei_nova_12i-12882.php"},
{"name": "nova 12 SE", "url": "https://www.gsmarena.com/huawei_nova_12_se-12881.php"},
{"name": "nova 12s", "url": "https://www.gsmarena.com/huawei_nova_12s-12880.php"},
{"name": "Pocket 2", "url": "https://www.gsmarena.com/huawei_pocket_2-12837.php"},
{"name": "Enjoy 70z", "url": "https://www.gsmarena.com/huawei_enjoy_70z-12835.php"},
{"name": "nova Y72", "url": "https://www.gsmarena.com/huawei_nova_y72-12807.php"},
{"name": "nova 12 Ultra", "url": "https://www.gsmarena.com/huawei_nova_12_ultra-12761.php"},
{"name": "nova 12 Pro", "url": "https://www.gsmarena.com/huawei_nova_12_pro-12588.php"},
{"name": "nova 12", "url": "https://www.gsmarena.com/huawei_nova_12-12589.php"},
{"name": "nova 12 Lite", "url": "https://www.gsmarena.com/huawei_nova_12_lite-12762.php"},
{"name": "Enjoy 70", "url": "https://www.gsmarena.com/huawei_enjoy_70-12720.php"},
{"name": "MatePad Pro 11 (2024)", "url": "https://www.gsmarena.com/huawei_matepad_pro_11_(2024)-12713.php"},
{"name": "nova 11 SE", "url": "https://www.gsmarena.com/huawei_nova_11_se-12648.php"},
{"name": "Watch Ultimate Design", "url": "https://www.gsmarena.com/huawei_watch_ultimate_design-12607.php"},
{"name": "MatePad Pro 13.2", "url": "https://www.gsmarena.com/huawei_matepad_pro_13_2-12586.php"},
{"name": "Mate 60 RS Ultimate", "url": "https://www.gsmarena.com/huawei_mate_60_rs_ultimate-12585.php"},
{"name": "Watch GT 4", "url": "https://www.gsmarena.com/huawei_watch_gt_4-12563.php"},
{"name": "Mate 60 Pro+", "url": "https://www.gsmarena.com/huawei_mate_60_pro+-12549.php"},
{"name": "Mate X5", "url": "https://www.gsmarena.com/huawei_mate_x5-12550.php"},
{"name": "Mate 60 Pro", "url": "https://www.gsmarena.com/huawei_mate_60_pro-12530.php"},
{"name": "Mate 60", "url": "https://www.gsmarena.com/huawei_mate_60-12539.php"},
{"name": "MatePad 11.5", "url": "https://www.gsmarena.com/huawei_matepad_11_5-12420.php"},
{"name": "MatePad Air", "url": "https://www.gsmarena.com/huawei_matepad_air-12415.php"},
{"name": "nova Y91", "url": "https://www.gsmarena.com/huawei_nova_y91-12290.php"},
{"name": "Watch 4 Pro", "url": "https://www.gsmarena.com/huawei_watch_4_pro-12278.php"},
{"name": "Watch 4", "url": "https://www.gsmarena.com/huawei_watch_4-12279.php"},
{"name": "nova 11i", "url": "https://www.gsmarena.com/huawei_nova_11i-12268.php"},
{"name": "nova Y71", "url": "https://www.gsmarena.com/huawei_nova_y71-12259.php"},
{"name": "Enjoy 60X", "url": "https://www.gsmarena.com/huawei_enjoy_60x-12235.php"},
{"name": "nova 11 Ultra", "url": "https://www.gsmarena.com/huawei_nova_11_ultra-12230.php"},
{"name": "nova 11 Pro", "url": "https://www.gsmarena.com/huawei_nova_11_pro-12233.php"},
{"name": "nova 11", "url": "https://www.gsmarena.com/huawei_nova_11-12234.php"},
{"name": "Mate X3", "url": "https://www.gsmarena.com/huawei_mate_x3-12186.php"},
{"name": "P60 Pro", "url": "https://www.gsmarena.com/huawei_p60_pro-12172.php"}
]